README.md
setup.py
gluware_ansible_inventory.egg-info/PKG-INFO
gluware_ansible_inventory.egg-info/SOURCES.txt
gluware_ansible_inventory.egg-info/dependency_links.txt
gluware_ansible_inventory.egg-info/top_level.txt
inventory/glu_devices.py
modules/glu_audit_config.py
modules/glu_capture_config.py
modules/glu_run_discover_device_attributes.py
modules/glu_update_device_attributes.py