Metadata-Version: 2.1
Name: gluware-ansible-inventory
Version: 1.2.0
Summary: Gluware Ansible Inventory
Home-page: https://gluware.com
Author: Gluware Inc.
Author-email: support@gluware.com
License: UNKNOWN
Platform: UNKNOWN
